LoudongYinxingDaKaMianduimianFenxiangHuizong114Qi/README.md
LoudongYinxingDaKaMianduimianFenxiangHuizong114Qi/__init__.py
LoudongYinxingDaKaMianduimianFenxiangHuizong114Qi/__main__.py
LoudongYinxingDaKaMianduimianFenxiangHuizong114Qi/file.epub
LoudongYinxingDaKaMianduimianFenxiangHuizong114Qi/index.html
LoudongYinxingDaKaMianduimianFenxiangHuizong114Qi/css/__init__.py
LoudongYinxingDaKaMianduimianFenxiangHuizong114Qi/css/annotations.css
LoudongYinxingDaKaMianduimianFenxiangHuizong114Qi/css/main.css
LoudongYinxingDaKaMianduimianFenxiangHuizong114Qi/css/normalize.css
LoudongYinxingDaKaMianduimianFenxiangHuizong114Qi/css/popup.css
LoudongYinxingDaKaMianduimianFenxiangHuizong114Qi/font/__init__.py
LoudongYinxingDaKaMianduimianFenxiangHuizong114Qi/font/fontello.eot
LoudongYinxingDaKaMianduimianFenxiangHuizong114Qi/font/fontello.svg
LoudongYinxingDaKaMianduimianFenxiangHuizong114Qi/font/fontello.ttf
LoudongYinxingDaKaMianduimianFenxiangHuizong114Qi/font/fontello.woff
LoudongYinxingDaKaMianduimianFenxiangHuizong114Qi/img/__init__.py
LoudongYinxingDaKaMianduimianFenxiangHuizong114Qi/img/annotator-glyph-sprite.png
LoudongYinxingDaKaMianduimianFenxiangHuizong114Qi/img/annotator-icon-sprite.png
LoudongYinxingDaKaMianduimianFenxiangHuizong114Qi/img/apple-touch-icon.png
LoudongYinxingDaKaMianduimianFenxiangHuizong114Qi/img/cancelfullscreen.png
LoudongYinxingDaKaMianduimianFenxiangHuizong114Qi/img/close.png
LoudongYinxingDaKaMianduimianFenxiangHuizong114Qi/img/fullscreen.png
LoudongYinxingDaKaMianduimianFenxiangHuizong114Qi/img/loader.gif
LoudongYinxingDaKaMianduimianFenxiangHuizong114Qi/img/menu-icon.png
LoudongYinxingDaKaMianduimianFenxiangHuizong114Qi/img/save.png
LoudongYinxingDaKaMianduimianFenxiangHuizong114Qi/img/saved.png
LoudongYinxingDaKaMianduimianFenxiangHuizong114Qi/img/settings-s.png
LoudongYinxingDaKaMianduimianFenxiangHuizong114Qi/img/settings.png
LoudongYinxingDaKaMianduimianFenxiangHuizong114Qi/img/star.png
loudong_yinxing_da_ka_mianduimian_fenxiang_huizong_1_14_qi-2024.3.2.0.dist-info/METADATA
loudong_yinxing_da_ka_mianduimian_fenxiang_huizong_1_14_qi-2024.3.2.0.dist-info/WHEEL
loudong_yinxing_da_ka_mianduimian_fenxiang_huizong_1_14_qi-2024.3.2.0.dist-info/entry_points.txt
loudong_yinxing_da_ka_mianduimian_fenxiang_huizong_1_14_qi-2024.3.2.0.dist-info/top_level.txt
loudong_yinxing_da_ka_mianduimian_fenxiang_huizong_1_14_qi-2024.3.2.0.dist-info/RECORD
