Metadata-Version: 2.1
Name: loudong-yinxing-da-ka-mianduimian-fenxiang-huizong-1-14-qi
Version: 2024.3.2.0
Summary: 漏洞银行“大咖面对面”分享汇总 1~14 期
Home-page: https://github.com/apachecn/loudong-yinxing-da-ka-mianduimian-fenxiang-huizong-1-14-qi
Author: ApacheCN
Author-email: apachecn@163.com
License: UNKNOWN
Platform: UNKNOWN
Classifier: Development Status :: 4 - Beta
Classifier: Environment :: Console
Classifier: Intended Audience :: Developers
Classifier: Intended Audience :: End Users/Desktop
Classifier: License :: Other/Proprietary License
Classifier: Natural Language :: Chinese (Simplified)
Classifier: Natural Language :: English
Classifier: Operating System :: OS Independent
Classifier: Programming Language :: Python :: 3
Classifier: Programming Language :: Python :: 3 :: Only
Classifier: Programming Language :: Python :: 3.6
Classifier: Programming Language :: Python :: 3.7
Classifier: Topic :: Text Processing :: Markup :: Markdown
Classifier: Topic :: Text Processing :: Markup :: HTML
Classifier: Topic :: Internet :: WWW/HTTP
Classifier: Topic :: Software Development :: Documentation
Classifier: Topic :: Documentation
Requires-Python: >=3.6
